{
  "model_id": "0xad2157ad6741f5e890f18d5a6b70e050f17dcc9203195bfe1f608418ff803059",
  "ipfs_hash": "QmZ845GwZBTLXvukPJbCeDMUzVUR345pQ5W6AXDES6vYbs",
  "round": "1.0.0520-3743.2",
  "version": 1747744299,
  "timestamp": 2,
  "participating_clients": "0xb6845ba34Fc592266921419ef65b9b4D943e2797",
  "model_info": {
    "round": 2,
    "timestamp": "2025-05-20T12:31:36.959967+00:00",
    "version": "1.0.0520-3743.2",
    "base_model_names": [
      "lr",
      "svc",
      "rf",
      "knn",
      "catboost",
      "lgbm",
      "xgb"
    ],
    "participating_clients": 2,
    "total_data_points": 101092,
    "average_score": 0.0
  }
}