{
  "model_id": "0x59236db1fa74b4f6de5232a390d74b0a77f0d7b83676c95b33a22e0c93053905",
  "ipfs_hash": "Qmdw6Dj6S3pVeT2A4cgpDMubQ12jATQ5K1GhnKJxVJSnsi",
  "round": "1.0.0521-9740.1",
  "version": 1747839873,
  "timestamp": 2,
  "participating_clients": "0xb6845ba34Fc592266921419ef65b9b4D943e2797",
  "model_info": {
    "round": 1,
    "timestamp": "2025-05-21T15:04:30.144828+00:00",
    "version": "1.0.0521-9740.1",
    "base_model_names": [
      "lr",
      "svc",
      "rf",
      "knn",
      "catboost",
      "lgbm",
      "xgb"
    ],
    "participating_clients": 2,
    "total_data_points": 34992,
    "average_score": 0.0
  }
}